scienceai/__init__.py
scienceai/__main__.py
scienceai/analyst.py
scienceai/analyst_base_prompt.txt
scienceai/backend.py
scienceai/bundle_validator.py
scienceai/bundle_validator_prompt.txt
scienceai/cli.py
scienceai/client.py
scienceai/data_extractor.py
scienceai/data_types.json
scienceai/data_types_docs.json
scienceai/database_manager.py
scienceai/llm.py
scienceai/llm_providers.py
scienceai/principal_investigator.py
scienceai/principal_investigator_base_prompt.txt
scienceai/process_paper.py
scienceai/py.typed
scienceai/reasoning.py
scienceai/scienceai-config.example.json
scienceai/prompts/analyst_append_anthropic.txt
scienceai/prompts/analyst_append_google.txt
scienceai/prompts/analyst_append_openai.txt
scienceai/prompts/analyst_prepend_anthropic.txt
scienceai/prompts/analyst_prepend_google.txt
scienceai/prompts/analyst_prepend_openai.txt
scienceai/prompts/pi_append_anthropic.txt
scienceai/prompts/pi_append_google.txt
scienceai/prompts/pi_append_openai.txt
scienceai/prompts/pi_prepend_anthropic.txt
scienceai/prompts/pi_prepend_google.txt
scienceai/prompts/pi_prepend_openai.txt
scienceai/static/apps.css
scienceai/static/main.js
scienceai/static/json-viewer/jquery.json-viewer.css
scienceai/static/json-viewer/jquery.json-viewer.js
scienceai/templates/app.html
scienceai/templates/chat.html
scienceai/templates/chat_update.html
scienceai/templates/close.html
scienceai/templates/create.html
scienceai/templates/db.html
scienceai/templates/db_element.html
scienceai/templates/menu.html
scienceai/templates/papers.html
scienceai/templates/save.html
scienceai_llm-0.4.6.dist-info/licenses/LICENSE
scienceai_llm-0.4.6.dist-info/METADATA
scienceai_llm-0.4.6.dist-info/WHEEL
scienceai_llm-0.4.6.dist-info/entry_points.txt
scienceai_llm-0.4.6.dist-info/top_level.txt
scienceai_llm-0.4.6.dist-info/RECORD
