Metadata-Version: 2.4
Name: scienceai-llm
Version: 0.4.6
Summary: An AI powered scientific literature search engine
Author-email: Elias Weston-Farber <elias@eliastechlabs.com>
Project-URL: Homepage, https://github.com/elias-jhsph/scienceai
Project-URL: Repository, https://github.com/elias-jhsph/scienceai
Project-URL: Documentation, https://github.com/elias-jhsph/scienceai#readme
Project-URL: Issues, https://github.com/elias-jhsph/scienceai/issues
Keywords: ai,science,research,literature,pdf,extraction,llm,openai,anthropic,gemini
Classifier: Development Status :: 4 - Beta
Classifier: Intended Audience :: Science/Research
Classifier: Programming Language :: Python :: 3
Classifier: Programming Language :: Python :: 3.11
Classifier: Programming Language :: Python :: 3.12
Classifier: License :: OSI Approved :: GNU General Public License v3 (GPLv3)
Classifier: Operating System :: OS Independent
Classifier: Topic :: Scientific/Engineering
Classifier: Topic :: Text Processing :: General
Classifier: Typing :: Typed
Requires-Python: >=3.11
License-File: LICENSE
Requires-Dist: PyMuPDF>=1.24.5
Requires-Dist: openai>=1.55.0
Requires-Dist: tiktoken>=0.7.0
Requires-Dist: habanero>=1.2.6
Requires-Dist: flask>=3.0.3
Requires-Dist: flask-sock>=0.7.0
Requires-Dist: dictdatabase>=2.5.0
Requires-Dist: pandas>=2.2.2
Requires-Dist: markdown2>=2.5.0
Requires-Dist: pillow>=11.0.0
Requires-Dist: pytesseract>=0.3.13
Requires-Dist: tabulate
Requires-Dist: matplotlib
Requires-Dist: scipy
Requires-Dist: seaborn
Requires-Dist: numpy
Requires-Dist: num2words
Requires-Dist: google-auth>=2.25.0
Requires-Dist: requests>=2.31.0
Provides-Extra: anthropic
Requires-Dist: anthropic>=0.40.0; extra == "anthropic"
Provides-Extra: google
Requires-Dist: google-genai>=1.0.0; extra == "google"
Provides-Extra: vertex-ai
Requires-Dist: google-cloud-aiplatform>=1.40.0; extra == "vertex-ai"
Requires-Dist: google-auth>=2.25.0; extra == "vertex-ai"
Provides-Extra: all-providers
Requires-Dist: anthropic[vertex]>=0.40.0; extra == "all-providers"
Requires-Dist: google-genai>=1.0.0; extra == "all-providers"
Requires-Dist: google-cloud-aiplatform>=1.40.0; extra == "all-providers"
Requires-Dist: google-auth>=2.25.0; extra == "all-providers"
Provides-Extra: dev
Requires-Dist: pytest>=7.4.0; extra == "dev"
Requires-Dist: pytest-cov>=4.1.0; extra == "dev"
Requires-Dist: pytest-asyncio>=0.21.0; extra == "dev"
Requires-Dist: ruff>=0.1.6; extra == "dev"
Requires-Dist: mypy>=1.7.0; extra == "dev"
Requires-Dist: pre-commit>=3.5.0; extra == "dev"
Requires-Dist: types-Flask>=1.1.0; extra == "dev"
Requires-Dist: types-requests>=2.31.0; extra == "dev"
Requires-Dist: pandas-stubs>=2.0.0; extra == "dev"
Requires-Dist: anthropic[vertex]>=0.40.0; extra == "dev"
Requires-Dist: google-genai>=1.0.0; extra == "dev"
Requires-Dist: google-cloud-aiplatform>=1.40.0; extra == "dev"
Requires-Dist: google-auth>=2.25.0; extra == "dev"
Dynamic: license-file
